<?xml version="1.0" encoding="UTF-8" standalone="yes"?>
<restInterface>
    <method>GET</method>
    <path>/multipleChoice</path>
    <queryParameters>orderBy, limit, offset, id, categoryId, name, description</queryParameters>
    <role>manager</role>
    <permissionAction>choice.read</permissionAction>
    <output>nabu.cms.choice.manage.rest.choice.multipleChoiceList</output>
    <lenient>false</lenient>
    <webApplicationId>false</webApplicationId>
    <language>false</language>
    <allowFormBinding>false</allowFormBinding>
    <caseInsensitive>false</caseInsensitive>
    <cache>false</cache>
    <allowCookiesWithoutReferer>false</allowCookiesWithoutReferer>
    <allowCookiesWithExternalReferer>false</allowCookiesWithExternalReferer>
    <request>false</request>
</restInterface>
